{
    "attachment_folder": "_v_attachments",
    "created_time": "2020-02-19T01:47:53Z",
    "files": [
    ],
    "image_folder": "",
    "recycle_bin_folder": "_v_recycle_bin",
    "sub_directories": [
        {
            "name": "_drafts"
        },
        {
            "name": "_posts"
        },
        {
            "name": "_v_recycle_bin"
        },
        {
            "name": "about"
        },
        {
            "name": "Achieve"
        },
        {
            "name": "category"
        },
        {
            "name": "link"
        },
        {
            "name": "project"
        },
        {
            "name": "sample-page"
        },
        {
            "name": "search"
        },
        {
            "name": "tag"
        }
    ],
    "tags": [
    ],
    "version": "1"
}
